{
  "schema_version": "shard-v1",
  "factpack_source": "/tmp/factpack_openstep42_proven_20260213",
  "function": {
    "entry": "0xf806f4a8",
    "name": "FUN_f806f4a8",
    "size": 52,
    "in_exec": true,
    "in_allow": true,
    "in_deny": false,
    "confidence_source": "default",
    "has_unresolved_bri": true
  },
  "blocks": [
    {
      "func_entry": "0xf806f4a8",
      "block_start": "0xf806f4a8",
      "block_end": "0xf806f4d3",
      "insn_count": 11
    },
    {
      "func_entry": "0xf806f4a8",
      "block_start": "0xf806f4d4",
      "block_end": "0xf806f4db",
      "insn_count": 2
    }
  ],
  "edges": [
    {
      "src": "0xf806f4c0",
      "dst": "0xf806f4c4",
      "kind": "fallthrough",
      "delay_slot": false
    },
    {
      "src": "0xf806f4bc",
      "dst": "0xf806f4c0",
      "kind": "fallthrough",
      "delay_slot": false
    },
    {
      "src": "0xf806f4c4",
      "dst": "0xf806f4c8",
      "kind": "fallthrough",
      "delay_slot": false
    },
    {
      "src": "0xf806f4a8",
      "dst": "0xf806f4ac",
      "kind": "fallthrough",
      "delay_slot": false
    },
    {
      "src": "0xf806f4c8",
      "dst": "0xf806f4cc",
      "kind": "fallthrough",
      "delay_slot": false
    },
    {
      "src": "0xf806f4ac",
      "dst": "0xf806f4b0",
      "kind": "fallthrough",
      "delay_slot": false
    },
    {
      "src": "0xf806f4cc",
      "dst": "0xf80694d0",
      "kind": "branch_cond",
      "delay_slot": true
    },
    {
      "src": "0xf806f4cc",
      "dst": "0xf806f4d4",
      "kind": "fallthrough",
      "delay_slot": false
    },
    {
      "src": "0xf806f4b0",
      "dst": "0xf806f4b4",
      "kind": "fallthrough",
      "delay_slot": false
    },
    {
      "src": "0xf806f4d0",
      "dst": "0xf806f4d4",
      "kind": "fallthrough",
      "delay_slot": false
    },
    {
      "src": "0xf806f4b4",
      "dst": "0xf806f4b8",
      "kind": "fallthrough",
      "delay_slot": false
    },
    {
      "src": "0xf806f4d4",
      "dst": null,
      "kind": "indirect",
      "delay_slot": true
    },
    {
      "src": "0xf806f4b8",
      "dst": "0xf806f4bc",
      "kind": "fallthrough",
      "delay_slot": false
    },
    {
      "src": "0xf806f4d8",
      "dst": "0xf806f4dc",
      "kind": "fallthrough",
      "delay_slot": false
    }
  ],
  "insns": [
    {
      "addr": "0xf806f4a8",
      "func_entry": "0xf806f4a8",
      "word": "0x9c3d0000",
      "mnemonic": "subs",
      "operands": "subs 0x0,r1,r29",
      "defs": [
        "r29"
      ],
      "uses": [
        "0x0",
        "r1"
      ],
      "pcode_ops": [
        "INT_SEXT",
        "INT_SUB"
      ],
      "flows": [],
      "mmio_tag": null,
      "string_ref": null
    },
    {
      "addr": "0xf806f4ac",
      "func_entry": "0xf806f4a8",
      "word": "0x09ff0906",
      "mnemonic": "ixfr",
      "operands": "ixfr r1,f31",
      "defs": [
        "f31"
      ],
      "uses": [
        "r1"
      ],
      "pcode_ops": [
        "COPY"
      ],
      "flows": [],
      "mmio_tag": null,
      "string_ref": null
    },
    {
      "addr": "0xf806f4b0",
      "func_entry": "0xf806f4a8",
      "word": "0x4d540007",
      "mnemonic": "unlock",
      "operands": "unlock",
      "defs": [],
      "uses": [
        "0x3"
      ],
      "pcode_ops": [
        "CALLOTHER"
      ],
      "flows": [],
      "mmio_tag": null,
      "string_ref": null
    },
    {
      "addr": "0xf806f4b4",
      "func_entry": "0xf806f4a8",
      "word": "0xa03d0000",
      "mnemonic": "shl",
      "operands": "shl r0,r1,r29",
      "defs": [
        "r29"
      ],
      "uses": [
        "0x0",
        "r1"
      ],
      "pcode_ops": [
        "INT_LEFT"
      ],
      "flows": [],
      "mmio_tag": null,
      "string_ref": null
    },
    {
      "addr": "0xf806f4b8",
      "func_entry": "0xf806f4a8",
      "word": "0x08fd0802",
      "mnemonic": "ixfr",
      "operands": "ixfr r1,f29",
      "defs": [
        "f29"
      ],
      "uses": [
        "r1"
      ],
      "pcode_ops": [
        "COPY"
      ],
      "flows": [],
      "mmio_tag": null,
      "string_ref": null
    },
    {
      "addr": "0xf806f4bc",
      "func_entry": "0xf806f4a8",
      "word": "0x30300007",
      "mnemonic": "ld.c",
      "operands": "ld.c psr,r16",
      "defs": [
        "r16"
      ],
      "uses": [
        "psr"
      ],
      "pcode_ops": [
        "COPY"
      ],
      "flows": [],
      "mmio_tag": null,
      "string_ref": null
    },
    {
      "addr": "0xf806f4c0",
      "func_entry": "0xf806f4a8",
      "word": "0xac3d0000",
      "mnemonic": "shr",
      "operands": "shr 0x0,r1,r29",
      "defs": [
        "r29"
      ],
      "uses": [
        "0x0",
        "r1"
      ],
      "pcode_ops": [
        "INT_RIGHT"
      ],
      "flows": [],
      "mmio_tag": null,
      "string_ref": null
    },
    {
      "addr": "0xf806f4c4",
      "func_entry": "0xf806f4a8",
      "word": "0x06fd0902",
      "mnemonic": "ld.b",
      "operands": "ld.b 0x902(r23),r29",
      "defs": [
        "r29"
      ],
      "uses": [
        "0x902",
        "r23"
      ],
      "pcode_ops": [
        "INT_SEXT",
        "INT_ADD",
        "LOAD",
        "INT_ZEXT"
      ],
      "flows": [],
      "mmio_tag": null,
      "string_ref": null
    },
    {
      "addr": "0xf806f4c8",
      "func_entry": "0xf806f4a8",
      "word": "0x460a0007",
      "mnemonic": "trap",
      "operands": "trap r0,r16,r10",
      "defs": [],
      "uses": [
        "0x0",
        "r16"
      ],
      "pcode_ops": [
        "CALLOTHER"
      ],
      "flows": [],
      "mmio_tag": null,
      "string_ref": null
    },
    {
      "addr": "0xf806f4cc",
      "func_entry": "0xf806f4a8",
      "word": "0xb43d0000",
      "mnemonic": "bla",
      "operands": "bla r0,r1,0xf80694d0",
      "defs": [
        "CC",
        "r1",
        "f31"
      ],
      "uses": [
        "0x0",
        "CC",
        "r1"
      ],
      "pcode_ops": [
        "INT_NOTEQUAL",
        "INT_CARRY",
        "INT_ZEXT",
        "INT_ADD",
        "COPY",
        "CBRANCH"
      ],
      "flows": [
        "0xf80694d0"
      ],
      "mmio_tag": null,
      "string_ref": null
    },
    {
      "addr": "0xf806f4d0",
      "func_entry": "0xf806f4a8",
      "word": "0x08ff0807",
      "mnemonic": "_ixfr",
      "operands": "_ixfr r1,f31",
      "defs": [
        "f31"
      ],
      "uses": [
        "r1"
      ],
      "pcode_ops": [
        "COPY"
      ],
      "flows": [],
      "mmio_tag": null,
      "string_ref": null
    },
    {
      "addr": "0xf806f4d4",
      "func_entry": "0xf806f4a8",
      "word": "0x43300007",
      "mnemonic": "bri",
      "operands": "bri r0",
      "defs": [
        "r29"
      ],
      "uses": [
        "0x0",
        "r1"
      ],
      "pcode_ops": [
        "INT_AND",
        "BRANCHIND"
      ],
      "flows": [],
      "mmio_tag": null,
      "string_ref": null
    },
    {
      "addr": "0xf806f4d8",
      "func_entry": "0xf806f4a8",
      "word": "0xc03d0000",
      "mnemonic": "_and",
      "operands": "_and r0,r1,r29",
      "defs": [
        "r29"
      ],
      "uses": [
        "0x0",
        "r1"
      ],
      "pcode_ops": [
        "INT_AND"
      ],
      "flows": [],
      "mmio_tag": null,
      "string_ref": null
    }
  ],
  "refs": [
    {
      "from": "0xf806f4cc",
      "to": "0xf80694d0",
      "type": "CONDITIONAL_JUMP",
      "is_flow": true,
      "is_primary": true
    }
  ],
  "strings": [],
  "dispatch_unresolved": [
    {
      "addr": "0xf806f4d4",
      "func_entry": "0xf806f4a8",
      "mnemonic": "bri",
      "flow_type": "COMPUTED_JUMP",
      "phase2_classification": null
    }
  ],
  "callees": [],
  "callers": [],
  "context": {
    "r15_cluster": false,
    "mmio_accesses": [],
    "nearby_deny_ranges": [],
    "nearby_embedded_objects": [],
    "priority_tags": [
      "unresolved_bri"
    ]
  }
}